thuonglib/AES_CBC.py
thuonglib/AES_CTR.py
thuonglib/AES_GCM.py
thuonglib/HASH.py
thuonglib/RSA_OAEP.py
thuonglib/__init__.py
thuonglib/c_by_hand.py
thuonglib/delete_folder.py
thuonglib/divide_merge_file.py
thuonglib/encrypt_decrypt_file.py
thuonglib/fileSecurity.py
thuonglib/file_compression.py
thuonglib/math_lib.py
thuonglib/password_cipher.py
thuonglib/recycleBin.py
thuonglib/thuonglib.py
thuonglib/utilities.py
thuonglib-1.0.4.dist-info/METADATA
thuonglib-1.0.4.dist-info/WHEEL
thuonglib-1.0.4.dist-info/entry_points.txt
thuonglib-1.0.4.dist-info/top_level.txt
thuonglib-1.0.4.dist-info/RECORD
