Metadata-Version: 2.4
Name: thuonglib
Version: 1.0.4
Summary:  Utility by Tran Dinh Thuong
Home-page: https://github.com/qbquangb/thuonglib
Author: Tran Dinh Thuong
Author-email: qbquangbinh@gmail.com
Classifier: Programming Language :: Python :: 3
Classifier: Programming Language :: Python :: 3.7
Classifier: Programming Language :: Python :: 3.8
Classifier: Programming Language :: Python :: 3.9
Classifier: Operating System :: OS Independent
Requires-Python: >=3.7
Dynamic: author
Dynamic: author-email
Dynamic: classifier
Dynamic: description
Dynamic: description-content-type
Dynamic: home-page
Dynamic: requires-python
Dynamic: summary
